[
  {
    "name": "Flash Axe",
    "input": "↓ ↘ → + [[LP]] / [[MP]]",
    "damage": "-",
    "type": "-",
    "startup": "-",
    "active": "-",
    "recovery": "-",
    "block_advantage": "-",
    "description": "A slashing elbow attack. It's easy to use in combos or as a way of checking your opponent. The medium version can cancel into Prowler Stance when it hits.",
    "category": "Special Moves"
  },
  {
    "name": "Flash Chop",
    "input": "↓ ↘ → + [[HP]]",
    "damage": "-",
    "type": "-",
    "startup": "-",
    "active": "-",
    "recovery": "-",
    "block_advantage": "-",
    "description": "A lunging swinging attack. It turns the opponent around when it hits an opponent standing on the ground.",
    "category": "Special Moves"
  },
  {
    "name": "Aerial Knee Smash",
    "input": "→ ↓ ↘ + [[K]]",
    "damage": "-",
    "type": "-",
    "startup": "-",
    "active": "-",
    "recovery": "-",
    "block_advantage": "-",
    "description": "Jumps into the air and attacks with the knee. It grants immunity to jumping attacks, making it useful as an anti-air technique.",
    "category": "Special Moves"
  },
  {
    "name": "Power Bomb",
    "input": "→ ↘ ↓ ↙ ← + [[P]]",
    "damage": "-",
    "type": "-",
    "startup": "-",
    "active": "-",
    "recovery": "-",
    "block_advantage": "-",
    "description": "Grabs the opponent and drive them into the ground. Useful for slipping through an opponent's guard at close range. If this connects when the opponent has their back to you, it transitions into Power Drop.",
    "category": "Special Moves"
  },
  {
    "name": "Hyper Bomb",
    "input": "→",
    "damage": "-",
    "type": "-",
    "startup": "-",
    "active": "-",
    "recovery": "-",
    "block_advantage": "-",
    "description": "A transition attack from Overdrive Power Drop. Effective for attacking the opponent without switching sides.",
    "category": "Special Moves"
  },
  {
    "name": "Raging Spear",
    "input": "↓ ↘ → ↓ ↘ → + [[K]]",
    "damage": "-",
    "type": "-",
    "startup": "-",
    "active": "-",
    "recovery": "-",
    "block_advantage": "-",
    "description": "Springs forth with a devastating tackle from a crouching position. This move is invincible on startup, making it useful as a way to turn the tables.",
    "category": "Super Arts"
  },
  {
    "name": "Sledgecross Hammer",
    "input": "↓ ↙ ← ↓ ↙ ← + [[P]]",
    "damage": "-",
    "type": "-",
    "startup": "-",
    "active": "-",
    "recovery": "-",
    "block_advantage": "-",
    "description": "Crushes opponents with a heavy, forward-moving lariat. Produces a wall splat when it connects on an airborne opponent.",
    "category": "Super Arts"
  },
  {
    "name": "Omega Wing Buster",
    "input": "[[P]] [[P]]",
    "damage": "-",
    "type": "-",
    "startup": "-",
    "active": "-",
    "recovery": "-",
    "block_advantage": "-",
    "description": "A transition attack from Overdrive Power Drop. Useful for when you want to maximize your damage output.",
    "category": "Super Arts"
  },
  {
    "name": "The Final Prison",
    "input": "↓ ↘ → ↓ ↘ → + [[P]]",
    "damage": "-",
    "type": "-",
    "startup": "-",
    "active": "-",
    "recovery": "-",
    "block_advantage": "-",
    "description": "Chokes out the opponent after hitting them with a Flash Chop. Effective as a close-range reversal, or as a high damage option in combos.",
    "category": "Super Arts"
  },
  {
    "name": "Prowler Stance",
    "input": "↓ + [[P]] [[P]]",
    "damage": "-",
    "type": "-",
    "startup": "-",
    "active": "-",
    "recovery": "-",
    "block_advantage": "-",
    "description": "Adopt a very low, stationary fighting stance. While in this stance, each input performs a different technique.",
    "category": "Unique Attacks"
  },
  {
    "name": "Low Rush",
    "input": "→",
    "damage": "-",
    "type": "-",
    "startup": "-",
    "active": "-",
    "recovery": "-",
    "block_advantage": "-",
    "description": "A movement technique from Prowler Stance that moves Alex forward.",
    "category": "Unique Attacks"
  },
  {
    "name": "Low Retreat",
    "input": "←",
    "damage": "-",
    "type": "-",
    "startup": "-",
    "active": "-",
    "recovery": "-",
    "block_advantage": "-",
    "description": "A movement technique from Prowler Stance that moves Alex backward.",
    "category": "Unique Attacks"
  },
  {
    "name": "Slashing Elbow",
    "input": "→ + [[P]]",
    "damage": "-",
    "type": "-",
    "startup": "-",
    "active": "-",
    "recovery": "-",
    "block_advantage": "-",
    "description": "Attack the opponent with an elbow strike while moving forward. Launches the opponent on counter hit.",
    "category": "Unique Attacks"
  },
  {
    "name": "Palm Jab",
    "input": "[[LP]]",
    "damage": "-",
    "type": "-",
    "startup": "-",
    "active": "-",
    "recovery": "-",
    "block_advantage": "-",
    "description": "A quick attack from Prowler Stance, which can be either rapid canceled, or canceled into a special move.",
    "category": "Unique Attacks"
  },
  {
    "name": "Shoulder Launcher",
    "input": "[[MP]]",
    "damage": "-",
    "type": "-",
    "startup": "-",
    "active": "-",
    "recovery": "-",
    "block_advantage": "-",
    "description": "A upward-moving attack from Prowler Stance. Transitions to Falling Moon on counter hit.",
    "category": "Unique Attacks"
  },
  {
    "name": "Heavy Lariat",
    "input": "[[HP]]",
    "damage": "-",
    "type": "-",
    "startup": "-",
    "active": "-",
    "recovery": "-",
    "block_advantage": "-",
    "description": "An attack from Prowler Stance that allows you to move before your opponent even when blocked. Hold the button down to gain armor properties. Turns the opponent around on counter hit.",
    "category": "Unique Attacks"
  },
  {
    "name": "Tactical Hop",
    "input": "[[LK]]",
    "damage": "-",
    "type": "-",
    "startup": "-",
    "active": "-",
    "recovery": "-",
    "block_advantage": "-",
    "description": "A technique from Prowler Stance that allows you to jump into the air quickly. You're free to attack once you're in the air.",
    "category": "Unique Attacks"
  },
  {
    "name": "Air Stampede",
    "input": "[[MK]]",
    "damage": "-",
    "type": "-",
    "startup": "-",
    "active": "-",
    "recovery": "-",
    "block_advantage": "-",
    "description": "An attack from Prowler Stance that quickly brings you back to the ground after jumping up.",
    "category": "Unique Attacks"
  },
  {
    "name": "Sweep Combination",
    "input": "[[HK]] [[HK]]",
    "damage": "-",
    "type": "-",
    "startup": "-",
    "active": "-",
    "recovery": "-",
    "block_advantage": "-",
    "description": "A low attack from Prowler Stance. Transitions into Flying Suplex on counter hit.",
    "category": "Unique Attacks"
  },
  {
    "name": "Hyper Takedown",
    "input": "[[LP]] [[LK]]",
    "damage": "-",
    "type": "-",
    "startup": "-",
    "active": "-",
    "recovery": "-",
    "block_advantage": "-",
    "description": "An attack from Prowler Stance that performs a double leg takedown on the opponent. Transitions to Death Valley Bomb on Punish Counter.",
    "category": "Unique Attacks"
  },
  {
    "name": "Dangerous Armbar",
    "input": "↓ + [[LP]] [[LK]]",
    "damage": "-",
    "type": "-",
    "startup": "-",
    "active": "-",
    "recovery": "-",
    "block_advantage": "-",
    "description": "An attack from Prowler Stance that only hits standing opponents. Transitions to Spiral DDT on Punish Counter.",
    "category": "Unique Attacks"
  },
  {
    "name": "Chop",
    "input": "→ + [[MP]]",
    "damage": "-",
    "type": "-",
    "startup": "-",
    "active": "-",
    "recovery": "-",
    "block_advantage": "-",
    "description": "An overhead attack that cannot be blocked while crouching.",
    "category": "Unique Attacks"
  },
  {
    "name": "Oblique Stomp",
    "input": "← + [[MK]]",
    "damage": "-",
    "type": "-",
    "startup": "-",
    "active": "-",
    "recovery": "-",
    "block_advantage": "-",
    "description": "An attack that allows you to act before an opponent even if blocked. Hit this when your opponent's back is facing towards you to transition into Collapsing Driver.",
    "category": "Unique Attacks"
  },
  {
    "name": "Flying Cross Chop",
    "input": "↓ + [[HP]]",
    "damage": "-",
    "type": "-",
    "startup": "-",
    "active": "-",
    "recovery": "-",
    "block_advantage": "-",
    "description": "A surprise attack performed while airborne. Useful for surprise attacks or as a way to approach your opponent.",
    "category": "Unique Attacks"
  },
  {
    "name": "Palm Strikes",
    "input": "[[MP]] [[HP]]",
    "damage": "-",
    "type": "-",
    "startup": "-",
    "active": "-",
    "recovery": "-",
    "block_advantage": "-",
    "description": "A rapid series of attacks. Can transition into Prowler Stance when it connects.",
    "category": "Unique Attacks"
  },
  {
    "name": "Twisted Drop",
    "input": "↓ + [[LK]] ↓ + [[HK]]",
    "damage": "-",
    "type": "-",
    "startup": "-",
    "active": "-",
    "recovery": "-",
    "block_advantage": "-",
    "description": "A counter followed by a sequence of attacks. Can transition into Prowler Stance when it connects.",
    "category": "Unique Attacks"
  },
  {
    "name": "Arm Lock",
    "input": "N / → + [[LP]] [[LK]]",
    "damage": "-",
    "type": "-",
    "startup": "-",
    "active": "-",
    "recovery": "-",
    "block_advantage": "-",
    "description": "Grab and twist your opponent's arm before throwing them forward. Throws your opponent without switching places with them.",
    "category": "Throws"
  },
  {
    "name": "Guillotine Hammer",
    "input": "← + [[LP]] [[LK]]",
    "damage": "-",
    "type": "-",
    "startup": "-",
    "active": "-",
    "recovery": "-",
    "block_advantage": "-",
    "description": "Force the opponent off balance before attacking. Throws your opponent while switching places with them.",
    "category": "Throws"
  },
  {
    "name": "Illegal Knees",
    "input": "↓ + [[LP]] [[LK]]",
    "damage": "-",
    "type": "-",
    "startup": "-",
    "active": "-",
    "recovery": "-",
    "block_advantage": "-",
    "description": "Strikes the opponent's head with a knee strike. Throws your opponent without switching places with them.",
    "category": "Throws"
  },
  {
    "name": "Drive Impact: Lariat Kick",
    "input": "[[HP]] [[HK]]",
    "damage": "-",
    "type": "-",
    "startup": "-",
    "active": "-",
    "recovery": "-",
    "block_advantage": "-",
    "description": "Lunge forward with a powerful attack. Can be used to absorb an opponent's attack while launching your own offensive.",
    "category": "Common Moves"
  },
  {
    "name": "Drive Reversal: Headbutt",
    "input": "→ + [[HP]] [[HK]]",
    "damage": "-",
    "type": "-",
    "startup": "-",
    "active": "-",
    "recovery": "-",
    "block_advantage": "-",
    "description": "Can be used after blocking an attack to quickly turn a defensive position into an offensive one. Can also be used when recovering from a knockdown. The input can be held while downed to perform this when rising.",
    "category": "Common Moves"
  },
  {
    "name": "Drive Parry",
    "input": "[[MP]] [[MK]]",
    "damage": "-",
    "type": "-",
    "startup": "-",
    "active": "-",
    "recovery": "-",
    "block_advantage": "-",
    "description": "Adopt a stance that allows you to deflect all opponent strikes. This stance can be sustained by holding down the command used to activate it.",
    "category": "Common Moves"
  },
  {
    "name": "Parry Drive Rush",
    "input": "→ →",
    "damage": "-",
    "type": "-",
    "startup": "-",
    "active": "-",
    "recovery": "-",
    "block_advantage": "-",
    "description": "Immediately move forward from a Drive Parry stance. Normal or unique attacks performed while moving will have their properties changed.",
    "category": "Common Moves"
  },
  {
    "name": "Cancel Drive Rush",
    "input": "→ → / ( N / → ) + [[MP]] [[MK]]",
    "damage": "-",
    "type": "-",
    "startup": "-",
    "active": "-",
    "recovery": "-",
    "block_advantage": "-",
    "description": "Immediately move forward out of an attack. Can be performed during any special-cancelable move.",
    "category": "Common Moves"
  }
]